gdbmongo/__init__.py
gdbmongo/_version.py
gdbmongo/abseil_printers.py
gdbmongo/aligned_printer.py
gdbmongo/boost_printers.py
gdbmongo/bsonmisc_printer.py
gdbmongo/bsonobj_printer.py
gdbmongo/date_printer.py
gdbmongo/decorable_printer.py
gdbmongo/detect_toolchain.py
gdbmongo/gdbutil.py
gdbmongo/interaction.py
gdbmongo/libstdcxxutil.py
gdbmongo/lock_manager_printer.py
gdbmongo/objectid_printer.py
gdbmongo/printer_protocol.py
gdbmongo/static_immortal_printer.py
gdbmongo/status_printer.py
gdbmongo/stdlib_printers.py
gdbmongo/stdlib_printers.pyi
gdbmongo/stdlib_printers_loader.py
gdbmongo/stdlib_xmethods.py
gdbmongo/stdlib_xmethods.pyi
gdbmongo/string_data_printer.py
gdbmongo/thread_name_printer.py
gdbmongo/timestamp_printer.py
gdbmongo/uuid_printer.py
gdbmongo-0.16.0.dist-info/LICENSE
gdbmongo-0.16.0.dist-info/METADATA
gdbmongo-0.16.0.dist-info/WHEEL
gdbmongo-0.16.0.dist-info/top_level.txt
gdbmongo-0.16.0.dist-info/RECORD
