Metadata-Version: 2.2
Name: gdbmongo
Version: 0.16.0
Summary: GDB pretty printers and commands for debugging the MongoDB Server
Home-page: https://github.com/visemet/gdb-mongodb-server
Maintainer: Max Hirschhorn
Maintainer-email: max.hirschhorn@mongodb.com
License: Apache License, Version 2.0
Keywords: mongo,mongodb,gdb
Platform: linux
Classifier: Development Status :: 4 - Beta
Classifier: Intended Audience :: Developers
Classifier: License :: OSI Approved :: Apache Software License
Classifier: Operating System :: POSIX
Classifier: Programming Language :: Python :: 3
Classifier: Programming Language :: Python :: 3 :: Only
Classifier: Programming Language :: Python :: 3.9
Classifier: Programming Language :: Python :: 3.10
Classifier: Programming Language :: Python :: 3.11
Classifier: Topic :: Database
Classifier: Topic :: Database :: Database Engines/Servers
Classifier: Topic :: Software Development :: Debuggers
Requires-Python: >=3.9
License-File: LICENSE
